<annotation>
	<folder></folder>
	<filename>-13-12-2021-171748_jpg.rf.ed56c9bf47de5ad1861aeb6fcc735cfb.jpg</filename>
	<path>-13-12-2021-171748_jpg.rf.ed56c9bf47de5ad1861aeb6fcc735cfb.jpg</path>
	<source>
		<database>roboflow.ai</database>
	</source>
	<size>
		<width>640</width>
		<height>640</height>
		<depth>3</depth>
	</size>
	<segmented>0</segmented>
	<object>
		<name>Ustap pierwszenstwa</name>
		<pose>Unspecified</pose>
		<truncated>0</truncated>
		<difficult>0</difficult>
		<occluded>0</occluded>
		<bndbox>
			<xmin>216</xmin>
			<xmax>432</xmax>
			<ymin>231</ymin>
			<ymax>576</ymax>
		</bndbox>
	</object>
</annotation>
