<annotation>
	<folder></folder>
	<filename>-13-12-2021-170517_jpg.rf.2d8f50e9f9cdc25835025eba3a46e56a.jpg</filename>
	<path>-13-12-2021-170517_jpg.rf.2d8f50e9f9cdc25835025eba3a46e56a.jpg</path>
	<source>
		<database>roboflow.ai</database>
	</source>
	<size>
		<width>640</width>
		<height>640</height>
		<depth>3</depth>
	</size>
	<segmented>0</segmented>
	<object>
		<name>Droga z pierwszenstwem</name>
		<pose>Unspecified</pose>
		<truncated>0</truncated>
		<difficult>0</difficult>
		<occluded>0</occluded>
		<bndbox>
			<xmin>184</xmin>
			<xmax>463</xmax>
			<ymin>219</ymin>
			<ymax>612</ymax>
		</bndbox>
	</object>
</annotation>
