<annotation>
	<folder></folder>
	<filename>000062_jpg.rf.cc9f754b2590d5728d9b7f340d0f2f4a.jpg</filename>
	<path>000062_jpg.rf.cc9f754b2590d5728d9b7f340d0f2f4a.jpg</path>
	<source>
		<database>roboflow.ai</database>
	</source>
	<size>
		<width>640</width>
		<height>640</height>
		<depth>3</depth>
	</size>
	<segmented>0</segmented>
	<object>
		<name>Ograniczenie predkosci do 30</name>
		<pose>Unspecified</pose>
		<truncated>0</truncated>
		<difficult>0</difficult>
		<occluded>0</occluded>
		<bndbox>
			<xmin>66</xmin>
			<xmax>182</xmax>
			<ymin>344</ymin>
			<ymax>456</ymax>
		</bndbox>
	</object>
</annotation>
