<annotation>
	<folder></folder>
	<filename>00002_00013_00001_png_jpg.rf.85722bf2ad9b03a8fbd0a2b8ebea3141.jpg</filename>
	<path>00002_00013_00001_png_jpg.rf.85722bf2ad9b03a8fbd0a2b8ebea3141.jpg</path>
	<source>
		<database>roboflow.ai</database>
	</source>
	<size>
		<width>640</width>
		<height>640</height>
		<depth>3</depth>
	</size>
	<segmented>0</segmented>
	<object>
		<name>Ograniczenie predkosci do 50</name>
		<pose>Unspecified</pose>
		<truncated>0</truncated>
		<difficult>0</difficult>
		<occluded>0</occluded>
		<bndbox>
			<xmin>150</xmin>
			<xmax>533</xmax>
			<ymin>156</ymin>
			<ymax>534</ymax>
		</bndbox>
	</object>
</annotation>
