<annotation>
	<folder></folder>
	<filename>000761_jpg.rf.6306d8b272f620dc3f278b113ab6a0f5.jpg</filename>
	<path>000761_jpg.rf.6306d8b272f620dc3f278b113ab6a0f5.jpg</path>
	<source>
		<database>roboflow.ai</database>
	</source>
	<size>
		<width>640</width>
		<height>640</height>
		<depth>3</depth>
	</size>
	<segmented>0</segmented>
	<object>
		<name>Ograniczenie predkosci do 90</name>
		<pose>Unspecified</pose>
		<truncated>0</truncated>
		<difficult>0</difficult>
		<occluded>0</occluded>
		<bndbox>
			<xmin>305</xmin>
			<xmax>601</xmax>
			<ymin>3</ymin>
			<ymax>446</ymax>
		</bndbox>
	</object>
</annotation>
