<annotation>
	<folder></folder>
	<filename>001055_jpg.rf.427dc5184410654c0d04b080c05a97fa.jpg</filename>
	<path>001055_jpg.rf.427dc5184410654c0d04b080c05a97fa.jpg</path>
	<source>
		<database>roboflow.ai</database>
	</source>
	<size>
		<width>640</width>
		<height>640</height>
		<depth>3</depth>
	</size>
	<segmented>0</segmented>
	<object>
		<name>Ograniczenie predkosci do 100</name>
		<pose>Unspecified</pose>
		<truncated>0</truncated>
		<difficult>0</difficult>
		<occluded>0</occluded>
		<bndbox>
			<xmin>360</xmin>
			<xmax>589</xmax>
			<ymin>150</ymin>
			<ymax>434</ymax>
		</bndbox>
	</object>
</annotation>
