<annotation>
	<folder></folder>
	<filename>00230-1-_jpg.rf.86b972a1e7e217d8f3e11191144e67eb.jpg</filename>
	<path>00230-1-_jpg.rf.86b972a1e7e217d8f3e11191144e67eb.jpg</path>
	<source>
		<database>roboflow.ai</database>
	</source>
	<size>
		<width>640</width>
		<height>640</height>
		<depth>3</depth>
	</size>
	<segmented>0</segmented>
	<object>
		<name>Ograniczenie predkosci do 30</name>
		<pose>Unspecified</pose>
		<truncated>0</truncated>
		<difficult>0</difficult>
		<occluded>0</occluded>
		<bndbox>
			<xmin>458</xmin>
			<xmax>474</xmax>
			<ymin>314</ymin>
			<ymax>339</ymax>
		</bndbox>
	</object>
</annotation>
