<annotation>
	<folder></folder>
	<filename>00758-1-_jpg.rf.a260d9bf16a6af65a736753d2ae2d66c.jpg</filename>
	<path>00758-1-_jpg.rf.a260d9bf16a6af65a736753d2ae2d66c.jpg</path>
	<source>
		<database>roboflow.ai</database>
	</source>
	<size>
		<width>640</width>
		<height>640</height>
		<depth>3</depth>
	</size>
	<segmented>0</segmented>
	<object>
		<name>Ograniczenie predkosci do 120</name>
		<pose>Unspecified</pose>
		<truncated>0</truncated>
		<difficult>0</difficult>
		<occluded>0</occluded>
		<bndbox>
			<xmin>179</xmin>
			<xmax>196</xmax>
			<ymin>416</ymin>
			<ymax>442</ymax>
		</bndbox>
	</object>
	<object>
		<name>Ograniczenie predkosci do 120</name>
		<pose>Unspecified</pose>
		<truncated>0</truncated>
		<difficult>0</difficult>
		<occluded>0</occluded>
		<bndbox>
			<xmin>465</xmin>
			<xmax>484</xmax>
			<ymin>417</ymin>
			<ymax>442</ymax>
		</bndbox>
	</object>
	<object>
		<name>Zakaz wyprzedzania</name>
		<pose>Unspecified</pose>
		<truncated>0</truncated>
		<difficult>0</difficult>
		<occluded>0</occluded>
		<bndbox>
			<xmin>179</xmin>
			<xmax>197</xmax>
			<ymin>442</ymin>
			<ymax>471</ymax>
		</bndbox>
	</object>
	<object>
		<name>Zakaz wyprzedzania</name>
		<pose>Unspecified</pose>
		<truncated>0</truncated>
		<difficult>0</difficult>
		<occluded>0</occluded>
		<bndbox>
			<xmin>465</xmin>
			<xmax>484</xmax>
			<ymin>442</ymin>
			<ymax>467</ymax>
		</bndbox>
	</object>
</annotation>
