<annotation>
	<folder></folder>
	<filename>00849-1-_jpg.rf.0b58d5b548e3d3ed5bc8c1cc8e02db4e.jpg</filename>
	<path>00849-1-_jpg.rf.0b58d5b548e3d3ed5bc8c1cc8e02db4e.jpg</path>
	<source>
		<database>roboflow.ai</database>
	</source>
	<size>
		<width>640</width>
		<height>640</height>
		<depth>3</depth>
	</size>
	<segmented>0</segmented>
	<object>
		<name>Stop</name>
		<pose>Unspecified</pose>
		<truncated>0</truncated>
		<difficult>0</difficult>
		<occluded>0</occluded>
		<bndbox>
			<xmin>187</xmin>
			<xmax>213</xmax>
			<ymin>276</ymin>
			<ymax>325</ymax>
		</bndbox>
	</object>
</annotation>
