<annotation>
	<folder></folder>
	<filename>286_jpg.rf.277e728561eed845b9ae8549b9d11c1f.jpg</filename>
	<path>286_jpg.rf.277e728561eed845b9ae8549b9d11c1f.jpg</path>
	<source>
		<database>roboflow.ai</database>
	</source>
	<size>
		<width>640</width>
		<height>640</height>
		<depth>3</depth>
	</size>
	<segmented>0</segmented>
	<object>
		<name>Droga z pierwszenstwem</name>
		<pose>Unspecified</pose>
		<truncated>0</truncated>
		<difficult>0</difficult>
		<occluded>0</occluded>
		<bndbox>
			<xmin>254</xmin>
			<xmax>407</xmax>
			<ymin>42</ymin>
			<ymax>202</ymax>
		</bndbox>
	</object>
	<object>
		<name>Ustap pierwszenstwa</name>
		<pose>Unspecified</pose>
		<truncated>0</truncated>
		<difficult>0</difficult>
		<occluded>0</occluded>
		<bndbox>
			<xmin>279</xmin>
			<xmax>409</xmax>
			<ymin>181</ymin>
			<ymax>311</ymax>
		</bndbox>
	</object>
</annotation>
