<annotation>
	<folder></folder>
	<filename>lampu-merah-39-_jpg.rf.09e63892316c02462f9f84d57de94d0c.jpg</filename>
	<path>lampu-merah-39-_jpg.rf.09e63892316c02462f9f84d57de94d0c.jpg</path>
	<source>
		<database>roboflow.ai</database>
	</source>
	<size>
		<width>640</width>
		<height>640</height>
		<depth>3</depth>
	</size>
	<segmented>0</segmented>
	<object>
		<name>Czerwone swiatlo</name>
		<pose>Unspecified</pose>
		<truncated>0</truncated>
		<difficult>0</difficult>
		<occluded>0</occluded>
		<bndbox>
			<xmin>1</xmin>
			<xmax>20</xmax>
			<ymin>254</ymin>
			<ymax>330</ymax>
		</bndbox>
	</object>
	<object>
		<name>Czerwone swiatlo</name>
		<pose>Unspecified</pose>
		<truncated>0</truncated>
		<difficult>0</difficult>
		<occluded>0</occluded>
		<bndbox>
			<xmin>184</xmin>
			<xmax>225</xmax>
			<ymin>162</ymin>
			<ymax>196</ymax>
		</bndbox>
	</object>
	<object>
		<name>Czerwone swiatlo</name>
		<pose>Unspecified</pose>
		<truncated>0</truncated>
		<difficult>0</difficult>
		<occluded>0</occluded>
		<bndbox>
			<xmin>450</xmin>
			<xmax>471</xmax>
			<ymin>247</ymin>
			<ymax>288</ymax>
		</bndbox>
	</object>
</annotation>
