<annotation>
	<folder></folder>
	<filename>lampu-merah-55-_jpg.rf.c10813d892624cd56b1d337032660d64.jpg</filename>
	<path>lampu-merah-55-_jpg.rf.c10813d892624cd56b1d337032660d64.jpg</path>
	<source>
		<database>roboflow.ai</database>
	</source>
	<size>
		<width>640</width>
		<height>640</height>
		<depth>3</depth>
	</size>
	<segmented>0</segmented>
	<object>
		<name>Czerwone swiatlo</name>
		<pose>Unspecified</pose>
		<truncated>0</truncated>
		<difficult>0</difficult>
		<occluded>0</occluded>
		<bndbox>
			<xmin>378</xmin>
			<xmax>550</xmax>
			<ymin>24</ymin>
			<ymax>615</ymax>
		</bndbox>
	</object>
</annotation>
