<annotation>
	<folder></folder>
	<filename>lampu-hijau-99-_jpg.rf.6933bf5b7087585edfc3d5a40288d7a2.jpg</filename>
	<path>lampu-hijau-99-_jpg.rf.6933bf5b7087585edfc3d5a40288d7a2.jpg</path>
	<source>
		<database>roboflow.ai</database>
	</source>
	<size>
		<width>640</width>
		<height>640</height>
		<depth>3</depth>
	</size>
	<segmented>0</segmented>
	<object>
		<name>Zielone swiatlo</name>
		<pose>Unspecified</pose>
		<truncated>0</truncated>
		<difficult>0</difficult>
		<occluded>0</occluded>
		<bndbox>
			<xmin>162</xmin>
			<xmax>278</xmax>
			<ymin>133</ymin>
			<ymax>550</ymax>
		</bndbox>
	</object>
</annotation>
