<annotation>
	<folder></folder>
	<filename>lampu-hijau-44-_jpg.rf.180434524dc23844e0f0c808afd16245.jpg</filename>
	<path>lampu-hijau-44-_jpg.rf.180434524dc23844e0f0c808afd16245.jpg</path>
	<source>
		<database>roboflow.ai</database>
	</source>
	<size>
		<width>640</width>
		<height>640</height>
		<depth>3</depth>
	</size>
	<segmented>0</segmented>
	<object>
		<name>Zielone swiatlo</name>
		<pose>Unspecified</pose>
		<truncated>0</truncated>
		<difficult>0</difficult>
		<occluded>0</occluded>
		<bndbox>
			<xmin>247</xmin>
			<xmax>334</xmax>
			<ymin>110</ymin>
			<ymax>321</ymax>
		</bndbox>
	</object>
	<object>
		<name>Zielone swiatlo</name>
		<pose>Unspecified</pose>
		<truncated>0</truncated>
		<difficult>0</difficult>
		<occluded>0</occluded>
		<bndbox>
			<xmin>536</xmin>
			<xmax>619</xmax>
			<ymin>158</ymin>
			<ymax>358</ymax>
		</bndbox>
	</object>
</annotation>
