<annotation>
	<folder></folder>
	<filename>larangan-berjalan-terus-wajib-berhenti-sesaat-77-_jpg.rf.a0083b905e650d1ce229604c82eac239.jpg</filename>
	<path>larangan-berjalan-terus-wajib-berhenti-sesaat-77-_jpg.rf.a0083b905e650d1ce229604c82eac239.jpg</path>
	<source>
		<database>roboflow.ai</database>
	</source>
	<size>
		<width>640</width>
		<height>640</height>
		<depth>3</depth>
	</size>
	<segmented>0</segmented>
	<object>
		<name>Stop</name>
		<pose>Unspecified</pose>
		<truncated>0</truncated>
		<difficult>0</difficult>
		<occluded>0</occluded>
		<bndbox>
			<xmin>446</xmin>
			<xmax>510</xmax>
			<ymin>235</ymin>
			<ymax>391</ymax>
		</bndbox>
	</object>
</annotation>
