<annotation>
	<folder></folder>
	<filename>larangan-masuk-bagi-kendaraan-bermotor-dan-tidak-bermotor-16-_jpg.rf.c399dc0a59626f1c4a1dd6539b17618c.jpg</filename>
	<path>larangan-masuk-bagi-kendaraan-bermotor-dan-tidak-bermotor-16-_jpg.rf.c399dc0a59626f1c4a1dd6539b17618c.jpg</path>
	<source>
		<database>roboflow.ai</database>
	</source>
	<size>
		<width>640</width>
		<height>640</height>
		<depth>3</depth>
	</size>
	<segmented>0</segmented>
	<object>
		<name>Zakaz wjazdu</name>
		<pose>Unspecified</pose>
		<truncated>0</truncated>
		<difficult>0</difficult>
		<occluded>0</occluded>
		<bndbox>
			<xmin>216</xmin>
			<xmax>450</xmax>
			<ymin>125</ymin>
			<ymax>434</ymax>
		</bndbox>
	</object>
</annotation>
