<annotation>
	<folder></folder>
	<filename>peringatan-banyak-pejalan-kaki-menggunakan-zebra-cross-57-_jpg.rf.f3ffc61eab9d1ee662119d5dda4c2676.jpg</filename>
	<path>peringatan-banyak-pejalan-kaki-menggunakan-zebra-cross-57-_jpg.rf.f3ffc61eab9d1ee662119d5dda4c2676.jpg</path>
	<source>
		<database>roboflow.ai</database>
	</source>
	<size>
		<width>640</width>
		<height>640</height>
		<depth>3</depth>
	</size>
	<segmented>0</segmented>
	<object>
		<name>Przejscie dla pieszych</name>
		<pose>Unspecified</pose>
		<truncated>0</truncated>
		<difficult>0</difficult>
		<occluded>0</occluded>
		<bndbox>
			<xmin>143</xmin>
			<xmax>484</xmax>
			<ymin>50</ymin>
			<ymax>426</ymax>
		</bndbox>
	</object>
</annotation>
