<annotation>
	<folder></folder>
	<filename>Screenshot_312_png.rf.282003c053c67438b2033e55ca97d594.jpg</filename>
	<path>Screenshot_312_png.rf.282003c053c67438b2033e55ca97d594.jpg</path>
	<source>
		<database>roboflow.ai</database>
	</source>
	<size>
		<width>640</width>
		<height>640</height>
		<depth>3</depth>
	</size>
	<segmented>0</segmented>
	<object>
		<name>Stop</name>
		<pose>Unspecified</pose>
		<truncated>0</truncated>
		<difficult>0</difficult>
		<occluded>0</occluded>
		<bndbox>
			<xmin>334</xmin>
			<xmax>356</xmax>
			<ymin>426</ymin>
			<ymax>503</ymax>
		</bndbox>
	</object>
</annotation>
